[
  {
    "title": "Metior",
    "repository": "http://github.com/cvdlab/metior",
    "description": "Web BIM platform to support surveyors creating 2D floorplans and 3D building models",
    "year": 2016,
    "tags": []
  },
  {
    "title": "TourBox",
    "repository": "http://github.com/cvdlab/tourbox",
    "description": "Web BIM platform to support surveyors creating 2D floorplans and 3D building models",
    "year": 2016,
    "tags": []
  },
  {
    "title": "ForesterJS",
    "repository": "http://github.com/foresterjs",
    "description": "NodeJS REST API Framework based on ES7 async/await paradigm",
    "year": 2016,
    "tags": ["NodeJS", "REST", "API", "Framework", "ES7", "async/await"]
  },
  {
    "title": "PantareiJS",
    "repository": "http://github.com/pantareijs",
    "description": "Web UI Framework based on Web Components",
    "year": 2016,
    "tags": ["Web", "UI", "Framework", "WebComponents"]
  },
  {
    "title": "BAK3D",
    "repository": "http://github.com/cvdlab",
    "description": "Web Platform to create quasi-photorealistic 3D indoor scenes based on texture baking techniques",
    "year": 2015,
    "tags": ["WebPlatform", "Photorealistic", "Indoor", "TextureBaking"]
  },
  {
    "title": "x-commerce",
    "repository": "http://github.com/x-project/x-commerce",
    "description": "Web Platform to build API-driven WebComponents-based HTML5 SPA e-commerce Applications",
    "year": 2015,
    "tags": ["WebPlatform", "NodeJS", "MongoDB", "API", "RESTful", "JWT", "HTML5", "WebComponents", "e-commerce"]
  },
  {
    "title": "x-learning",
    "repository": "http://github.com/x-project/x-learning",
    "description": "Web Platform to build API-driven HTML5 Single Page e-learning Applications",
    "year": 2015,
    "tags": ["WebPlatform", "NodeJS", "MongoDB", "API", "RESTful", "JWT", "HTML5", "WebComponents", "e-learning", "MOOC"]
  },
  {
    "title": "x-project",
    "repository": "http://github.com/x-project/x-project",
    "description": "Web Platform to build API-driven WebComponents-based HTML5 SinglePageApplications",
    "year": 2015,
    "tags": ["WebPlatform", "NodeJS", "MongoDB", "API", "RESTful", "JWT", "HTML5", "WebComponents"]
  },
  {
    "title": "x-journal",
    "repository": "http://github.com/x-project/x-journal",
    "description": "Web Platform to build API-driven HTML5 Single Page e-journal Applications",
    "year": 2015,
    "tags": ["WebPlatform", "NodeJS", "MongoDB", "API", "RESTful", "JWT", "HTML5", "WebComponents", "e-journal"]
  },
  {
    "title": "C3D",
    "repository": "http://github.com/cvdlab/c3d",
    "description": "Web Platform to build interactive VR indoor mapping and real-time IoT monitoring",
    "year": 2015,
    "tags": ["WebPlatform", "VR", "IndoorMapping", "IoT"]
  },
  {
    "title": "DMA.js",
    "description": "JavaScript Decision Making Assistant library based on multi-criteria methods",
    "year": 2014,
    "tags": ["JavaScript", "MultiCriteria", "DecisionMaking"]
  },
  {
    "title": "ServiceLink",
    "description": "Web Platform to create RESTful API-based services in a Visual Programming manner",
    "year": 2013,
    "tags": ["WebPlatform", "VisualProgramming", "NodeJS", "HTML5", "Drag&Drop", "RESTful", "services"]
  },
  {
    "title": "VisPro",
    "description": "Web Platform to create simple Web Applications without writing code",
    "year": 2012,
    "tags": ["WebPlatform", "VisualProgramming", "HTML5", "widgets"]
  },
  {
    "title": "LAR.js",
    "description": "JavaScript multi-dimensional geometric kernel based on linear algebraic representation for 3D solid modelling",
    "year": 2011,
    "tags": ["JavaScript", "SolidModelling", "GeometricKernel", "LinearAlgebraicRepresentation"]
  },
  {
    "title": "Simplexn.js",
    "repository": "http://github.com/cvdlab/simplexn.js",
    "description": "JavaScript multi-dimensional geometric kernel based on simplicial complex for 3D solid modelling",
    "year": 2011,
    "tags": ["JavaScript", "SolidModelling", "GeometricKernel", "Simplex", "SimplicialComplex"]
  },
  {
    "title": "Plasm.js",
    "repository": "https://github.com/cvdlab/plasm.js",
    "description": "JavaScript functional programming library for solid modelling based on dimension-independent geometric kernel",
    "url": "http://cvdlab.github.io/plasm.js/",
    "year": 2011,
    "tags": ["JavaScript", "FunctionalProgramming", "SolidModelling", "GeometricKernel"]
  }
]
